README.rst
setup.py
pycdl/__init__.py
pycdl.egg-info/PKG-INFO
pycdl.egg-info/SOURCES.txt
pycdl.egg-info/dependency_links.txt
pycdl.egg-info/top_level.txt