Metadata-Version: 1.1
Name: pycdl
Version: 0.5.4
Summary: Simple CDL reading library
Home-page: https://github.com/simonh10/pycdl
Author: Simon Hargreaves
Author-email: simon@simon-hargreaves.com
License: MIT
Keywords: color cdl edl decision list avid
Platform: UNKNOWN
Classifier: Development Status :: 4 - Beta
Classifier: Environment :: Console
Classifier: Intended Audience :: Developers
Classifier: License :: OSI Approved :: MIT License
Classifier: Operating System :: MacOS :: MacOS X
Classifier: Operating System :: Microsoft :: Windows
Classifier: Operating System :: POSIX
Classifier: Programming Language :: Python
Classifier: Natural Language :: English
Classifier: Topic :: Multimedia :: Video
Classifier: Topic :: Software Development :: Libraries
